stormsvala/column.py
stormsvala/driver.py
stormsvala/path.py
stormsvala/table.py
stormsvala-0.0.3.dist-info/LICENSE
stormsvala-0.0.3.dist-info/METADATA
stormsvala-0.0.3.dist-info/WHEEL
stormsvala-0.0.3.dist-info/top_level.txt
stormsvala-0.0.3.dist-info/RECORD
