Metadata-Version: 2.1
Name: stormsvala
Version: 0.0.3
Summary: Helpful module for interacting with postgres
Author-email: Erik Bremstedt <erik.bremstedt@gmail.com>
Project-URL: Homepage, https://github.com/ebremstedt/stormsvala
Project-URL: Issues, https://github.com/ebremstedt/stormsvala/issues
Classifier: Programming Language :: Python :: 3
Classifier: License :: OSI Approved :: MIT License
Classifier: Operating System :: OS Independent
Requires-Python: >=3.8
License-File: LICENSE
Requires-Dist: psycopg2-binary==2.9.9
